{"note":"Don't delete this file! It's used internally to help with page regeneration.","tagline":"A simple Objective-C Bar Chart / Histogram library.","name":"DSBarChart","google":"","body":"```                                                                                   \r\n______  ___________            _____ _                _   \r\n|  _  \\/  ___| ___ \\          /  __ \\ |              | |  \r\n| | | |\\ `--.| |_/ / __ _ _ __| /  \\/ |__   __ _ _ __| |_ \r\n| | | | `--. \\ ___ \\/ _` | '__| |   | '_ \\ / _` | '__| __|\r\n| |/ / /\\__/ / |_/ / (_| | |  | \\__/\\ | | | (_| | |  | |_ \r\n|___/  \\____/\\____/ \\__,_|_|   \\____/_| |_|\\__,_|_|   \\__|\r\n```\r\n\r\nA simple Objective-C Bar Chart / Histogram library.\r\n\r\nLatest Version: 0.4.0\r\n\r\n# Installation\r\n\r\n## Install manually\r\n\r\nSimply click [here](https://github.com/dhilipsiva/DSBarChart/archive/master.zip) to download the file and add it into your project directory.\r\n\r\n## Install using git\r\n\r\n1. Simply type `git clone git@github.com:dhilipsiva/DSBarChart.git` to clone this repo or `git submodule add git@github.com:dhilipsiva/DSBarChart.git` into your project folder.\r\n\r\n## Install using CocoaPods\r\n\r\nDSBarChart is also avilable on [CocoaPods](http://cocoapods.org/?q=dhilipsiva). To Install using CocoaPods, follow the instructions:\r\n\r\n1. Open your Podfile\r\n2. Append `pod 'DSBarChart',  '~> 0.4.0'`\r\n3. Type `pod install` on terminal\r\n4. Open your `.xcworkspace` file.\r\n\r\n# Sample Usage\r\n\r\n```objective-c\r\nNSArray *vals = [NSArray arrayWithObjects:\r\n                 [NSNumber numberWithInt:30],\r\n                 [NSNumber numberWithInt:40],\r\n                 [NSNumber numberWithInt:20],\r\n                 [NSNumber numberWithInt:56],\r\n                 [NSNumber numberWithInt:70],\r\n                 [NSNumber numberWithInt:34],\r\n                 [NSNumber numberWithInt:43],\r\n                 nil];\r\nNSArray *refs = [NSArray arrayWithObjects:@\"M\", @\"Tu\", @\"W\", @\"Th\", @\"F\", @\"Sa\", @\"Su\", nil];\r\nDSBarChart *chrt = [[DSBarChart alloc] initWithFrame:ChartView.bounds\r\n                                               color:[UIColor greenColor]\r\n                                          references:refs\r\n                                           andValues:vals];\r\nchrt.autoresizingMask = UIViewAutoresizingFlexibleWidth | UIViewAutoresizingFlexibleHeight;\r\nchrt.bounds = ChartView.bounds;\r\n[ChartView addSubview:chrt];\r\n```\r\n\r\n# Output of the sample code above\r\n\r\n<img src=\"https://raw.github.com/dhilipsiva/DSBarChart/master/DSBarChart.png\"\r\n alt=\"DSBarChart\" title=\"A simple objective-c Bar Chart / Histogram library.\" align=\"canter\"/>\r\n  \r\n# Who is using DSBarChart\r\n\r\n1. [ReWire](http://www.rewireapp.com/)\r\n\r\nIf you are using DSBarChart, please feel free to edit this list.\r\n\r\n# Credits\r\n\r\n1. [DhilipSiva](https://github.com/dhilipsiva)\r\n2. [Gautam Jeyaraman](https://github.com/gautamjeyaraman)\r\n\r\n# Support\r\n\r\n* Email:     dhilipsiva[at]gmail.com\r\n* Groups:    [Google Groups](https://groups.google.com/forum/?fromgroups#!forum/dsbarchart)\r\n\r\n# Final Note\r\n\r\nAs like many other developers, I would be happy if you give me an attribution if you use this. Drop a mail. Or buy me something from my wishlist:\r\n\r\n1. [Amazon](http://www.amazon.com/registry/wishlist/2E251JJU12H5T)\r\n2. [Flipkart](http://www.flipkart.com/wishlist/dhilipsiva)\r\n"}